setup.py
src/digimat/__init__.py
src/digimat.sankey.egg-info/PKG-INFO
src/digimat.sankey.egg-info/SOURCES.txt
src/digimat.sankey.egg-info/dependency_links.txt
src/digimat.sankey.egg-info/namespace_packages.txt
src/digimat.sankey.egg-info/not-zip-safe
src/digimat.sankey.egg-info/requires.txt
src/digimat.sankey.egg-info/top_level.txt
src/digimat/sankey/__init__.py
src/digimat/sankey/sankey.py