Metadata-Version: 1.0
Name: digimat.sankey
Version: 0.1.2
Summary: Digimat Sankey Diagrams
Home-page: UNKNOWN
Author: Frederic Hess
Author-email: fhess@splust.ch
License: PSF
Platform: UNKNOWN
